.VERSION
AUTHORS.rst
CONTRIBUTING.rst
HISTORY.rst
LICENSE
MANIFEST.in
Pipfile
Pipfile.lock
README.rst
USAGE.rst
dev-requirements.txt
requirements.txt
setup.cfg
setup.py
docs/Makefile
docs/authors.rst
docs/conf.py
docs/contributing.rst
docs/history.rst
docs/index.rst
docs/installation.rst
docs/readme.rst
docs/usage.rst
tests/test_wikiseriesstijnlib.py
wikiseriesstijnlib/.VERSION
wikiseriesstijnlib/AUTHORS.rst
wikiseriesstijnlib/CONTRIBUTING.rst
wikiseriesstijnlib/HISTORY.rst
wikiseriesstijnlib/LICENSE
wikiseriesstijnlib/Pipfile
wikiseriesstijnlib/Pipfile.lock
wikiseriesstijnlib/README.rst
wikiseriesstijnlib/USAGE.rst
wikiseriesstijnlib/__init__.py
wikiseriesstijnlib/_version.py
wikiseriesstijnlib/dev-requirements.txt
wikiseriesstijnlib/requirements.txt
wikiseriesstijnlib/wikiseriesstijnlib.py
wikiseriesstijnlib/wikiseriesstijnlibexceptions.py
wikiseriesstijnlib.egg-info/PKG-INFO
wikiseriesstijnlib.egg-info/SOURCES.txt
wikiseriesstijnlib.egg-info/dependency_links.txt
wikiseriesstijnlib.egg-info/not-zip-safe
wikiseriesstijnlib.egg-info/requires.txt
wikiseriesstijnlib.egg-info/top_level.txt