Metadata-Version: 2.1
Name: wikiseriesstijnlib
Version: 0.1.2
Summary: Library to use wikipedia to query tv series episode lists.
Home-page: https://github.com/Stijn-Daniels/wikiseriesstijnlib
Author: Stijn Daniels
Author-email: stijn.githubemail@gmail.com
License: MIT
Keywords: wikiseriesstijnlib
Classifier: Development Status :: 3 - Alpha
Classifier: Intended Audience :: Developers
Classifier: License :: OSI Approved :: MIT License
Classifier: Natural Language :: English
Classifier: Programming Language :: Python :: 3.9
License-File: LICENSE
License-File: AUTHORS.rst
